[
    {
        "id": "738",
        "company_name": "eversai Careers",
        "website": "www.eversai.com",
        "location_city": "Hyderabad, India",
        "stock": "1 to 50 employees",
        "industry": "Business Supplies & Equipment",
        "founding_year": "2019",
        "country": "India",
        "founding_date": "",
        "investors": "",
        "revenue": "",
        "sector": "",
        "absolute_growth_rate_pct": "",
        "compound_annual_growth_rate_cagr_pct": "",
        "employees_number": "",
        "market_cap": "",
        "ceo": "",
        "address": "",
        "telephone": "",
        "facebook": "",
        "twitter": "",
        "instagram": "",
        "pinterest": "",
        "sales": "",
        "assets": "",
        "area_served": "",
        "price": "",
        "income": "",
        "wikipedia": "",
        "hhid": "",
        "sic_code": "",
        "type": ""
    }
]