[
    {
        "address": "Via Domicella,63",
        "country": "Italy",
        "sector": "Vendita al dettaglio & all'ingrosso",
        "revenue": "1.994",
        "company_name": "Mr. Christmas S.r.l.",
        "id": "",
        "founding_date": "",
        "location_city": "Roma",
        "industry": "",
        "investors": "",
        "founding_year": "",
        "stock": "",
        "absolute_growth_rate_pct": "",
        "compound_annual_growth_rate_cagr_pct": "",
        "employees_number": "",
        "website": "",
        "market_cap": "",
        "ceo": "",
        "telephone": "",
        "facebook": "",
        "twitter": "",
        "instagram": "",
        "pinterest": "",
        "sales": "",
        "assets": "",
        "area_served": "",
        "price": "",
        "income": "",
        "wikipedia": "",
        "hhid": "",
        "sic_code": "",
        "type": ""
    },
    {
        "id": 1929,
        "company_name": "Mr. Cooper Group",
        "country": "United States",
        "sales": "$2.9 B",
        "revenue": "$1.42 B",
        "assets": "$14.2 B",
        "market_cap": "$3.35 B",
        "founding_date": "",
        "location_city": "United States",
        "industry": "",
        "investors": "",
        "founding_year": "",
        "stock": "",
        "sector": "",
        "absolute_growth_rate_pct": "",
        "compound_annual_growth_rate_cagr_pct": "",
        "employees_number": "",
        "website": "",
        "ceo": "",
        "address": "",
        "telephone": "",
        "facebook": "",
        "twitter": "",
        "instagram": "",
        "pinterest": "",
        "area_served": "",
        "price": "",
        "income": "",
        "wikipedia": "",
        "hhid": "",
        "sic_code": "",
        "type": ""
    },
    {
        "website": "https://www.forbes.com/companies/mr-cooper-group",
        "company_name": "Mr. Cooper Group",
        "industry": "Insurance",
        "founding_year": "1994",
        "country": "United States",
        "ceo": "Jesse K. Bray",
        "employees_number": "8,200",
        "revenue": "$2.9B",
        "id": "",
        "founding_date": "",
        "location_city": "United States",
        "investors": "",
        "stock": "",
        "sector": "",
        "absolute_growth_rate_pct": "",
        "compound_annual_growth_rate_cagr_pct": "",
        "market_cap": "",
        "address": "",
        "telephone": "",
        "facebook": "",
        "twitter": "",
        "instagram": "",
        "pinterest": "",
        "sales": "",
        "assets": "",
        "area_served": "",
        "price": "",
        "income": "",
        "wikipedia": "",
        "hhid": "",
        "sic_code": "",
        "type": ""
    },
    {
        "website": "https://disfold.com/company/mr-bricolage-sa/",
        "company_name": "Mr. Bricolage SA",
        "country": "France",
        "employees_number": "490",
        "ceo": "Mr. Christophe  Mistou",
        "market_cap": "\u20ac114.1 Million",
        "id": "",
        "founding_date": "",
        "location_city": "La Chapelle-Saint-Mesmin, France",
        "industry": "",
        "investors": "",
        "founding_year": "",
        "stock": "",
        "revenue": "",
        "sector": "",
        "absolute_growth_rate_pct": "",
        "compound_annual_growth_rate_cagr_pct": "",
        "address": "",
        "telephone": "",
        "facebook": "",
        "twitter": "",
        "instagram": "",
        "pinterest": "",
        "sales": "",
        "assets": "",
        "area_served": "",
        "price": "",
        "income": "",
        "wikipedia": "",
        "hhid": "",
        "sic_code": "",
        "type": ""
    },
    {
        "website": "https://disfold.com/company/mr-price-group-ltd/",
        "company_name": "Mr Price Group Ltd",
        "country": "South Africa",
        "employees_number": "17,831",
        "ceo": "Mr. Mark McNeil Blair",
        "market_cap": "R52.53 Billion",
        "id": "",
        "founding_date": "",
        "location_city": "Durban, South Africa",
        "industry": "",
        "investors": "",
        "founding_year": "",
        "stock": "",
        "revenue": "",
        "sector": "",
        "absolute_growth_rate_pct": "",
        "compound_annual_growth_rate_cagr_pct": "",
        "address": "",
        "telephone": "",
        "facebook": "",
        "twitter": "",
        "instagram": "",
        "pinterest": "",
        "sales": "",
        "assets": "",
        "area_served": "",
        "price": "",
        "income": "",
        "wikipedia": "",
        "hhid": "",
        "sic_code": "",
        "type": ""
    },
    {
        "company_name": "Mr. Cooper Group",
        "market_cap": "2960000000",
        "price": "42",
        "country": "United States",
        "id": "",
        "founding_date": "",
        "location_city": "USA",
        "industry": "",
        "investors": "",
        "founding_year": "",
        "stock": "",
        "revenue": "",
        "sector": "",
        "absolute_growth_rate_pct": "",
        "compound_annual_growth_rate_cagr_pct": "",
        "employees_number": "",
        "website": "",
        "ceo": "",
        "address": "",
        "telephone": "",
        "facebook": "",
        "twitter": "",
        "instagram": "",
        "pinterest": "",
        "sales": "",
        "assets": "",
        "area_served": "",
        "income": "",
        "wikipedia": "",
        "hhid": "",
        "sic_code": "",
        "type": ""
    },
    {
        "company_name": "Mr Price Group",
        "market_cap": "2430000000",
        "price": "10",
        "country": "South Africa",
        "id": "",
        "founding_date": "",
        "location_city": "South Africa",
        "industry": "",
        "investors": "",
        "founding_year": "",
        "stock": "",
        "revenue": "",
        "sector": "",
        "absolute_growth_rate_pct": "",
        "compound_annual_growth_rate_cagr_pct": "",
        "employees_number": "",
        "website": "",
        "ceo": "",
        "address": "",
        "telephone": "",
        "facebook": "",
        "twitter": "",
        "instagram": "",
        "pinterest": "",
        "sales": "",
        "assets": "",
        "area_served": "",
        "income": "",
        "wikipedia": "",
        "hhid": "",
        "sic_code": "",
        "type": ""
    },
    {
        "company_name": "Mrs Bector's Food Specialities",
        "industry": "FMCG",
        "country": "India",
        "founding_year": "1978",
        "id": "",
        "founding_date": "",
        "location_city": "Gurgaon, India",
        "investors": "",
        "stock": "",
        "revenue": "",
        "sector": "",
        "absolute_growth_rate_pct": "",
        "compound_annual_growth_rate_cagr_pct": "",
        "employees_number": "",
        "website": "",
        "market_cap": "",
        "ceo": "",
        "address": "",
        "telephone": "",
        "facebook": "",
        "twitter": "",
        "instagram": "",
        "pinterest": "",
        "sales": "",
        "assets": "",
        "area_served": "",
        "price": "",
        "income": "",
        "wikipedia": "",
        "hhid": "",
        "sic_code": "",
        "type": ""
    },
    {
        "company_name": "Mr Cooper",
        "industry": "Financial Services",
        "country": "United States",
        "founding_year": "1994",
        "id": "",
        "founding_date": "",
        "location_city": "Dallas, Texas, United States (USA)",
        "investors": "",
        "stock": "",
        "revenue": "",
        "sector": "",
        "absolute_growth_rate_pct": "",
        "compound_annual_growth_rate_cagr_pct": "",
        "employees_number": "",
        "website": "",
        "market_cap": "",
        "ceo": "",
        "address": "",
        "telephone": "",
        "facebook": "",
        "twitter": "",
        "instagram": "",
        "pinterest": "",
        "sales": "",
        "assets": "",
        "area_served": "",
        "price": "",
        "income": "",
        "wikipedia": "",
        "hhid": "",
        "sic_code": "",
        "type": ""
    },
    {
        "company_name": "Mr. Price Group Ltd",
        "country": "South Africa",
        "employees_number": "20,837",
        "address": "Upper Level, North Concourse, 65 Nmr Avenue, Durban, 4001",
        "industry": "Retailing",
        "website": "www.mrpricegroup.com",
        "market_cap": "$2.6B",
        "telephone": "27 31 3108000",
        "revenue": "$1.9B",
        "id": "",
        "founding_date": "",
        "location_city": "South Africa",
        "investors": "",
        "founding_year": "",
        "stock": "",
        "sector": "",
        "absolute_growth_rate_pct": "",
        "compound_annual_growth_rate_cagr_pct": "",
        "ceo": "",
        "facebook": "",
        "twitter": "",
        "instagram": "",
        "pinterest": "",
        "sales": "",
        "assets": "",
        "area_served": "",
        "price": "",
        "income": "",
        "wikipedia": "",
        "hhid": "",
        "sic_code": "",
        "type": ""
    },
    {
        "company_name": "Mr Cooper Group Inc",
        "country": "United States",
        "employees_number": "8,200",
        "address": "8950 Cypress Waters Blvd, Coppell, Texas, 75019",
        "industry": "Financial Services",
        "website": "www.mrcoopergroup.com",
        "market_cap": "$3.1B",
        "telephone": "1 214 6874958",
        "revenue": "$3.3B",
        "id": "",
        "founding_date": "",
        "location_city": "United States of America",
        "investors": "",
        "founding_year": "",
        "stock": "",
        "sector": "",
        "absolute_growth_rate_pct": "",
        "compound_annual_growth_rate_cagr_pct": "",
        "ceo": "",
        "facebook": "",
        "twitter": "",
        "instagram": "",
        "pinterest": "",
        "sales": "",
        "assets": "",
        "area_served": "",
        "price": "",
        "income": "",
        "wikipedia": "",
        "hhid": "",
        "sic_code": "",
        "type": ""
    }
]