[
    {
        "website": "https://disfold.com/company/x-trade-brokers-dom-maklerski-sa/",
        "company_name": "X-Trade Brokers Dom Maklerski SA",
        "country": "Poland",
        "employees_number": "532",
        "ceo": "Mr. Omar  Arnaout",
        "market_cap": "\u20ac484.6 Million",
        "id": "",
        "founding_date": "",
        "location_city": "Warsaw, Poland",
        "industry": "",
        "investors": "",
        "founding_year": "",
        "stock": "",
        "revenue": "",
        "sector": "",
        "absolute_growth_rate_pct": "",
        "compound_annual_growth_rate_cagr_pct": "",
        "address": "",
        "telephone": "",
        "facebook": "",
        "twitter": "",
        "instagram": "",
        "pinterest": "",
        "sales": "",
        "assets": "",
        "area_served": "",
        "price": "",
        "income": "",
        "wikipedia": "",
        "hhid": "",
        "sic_code": "",
        "type": ""
    },
    {
        "website": "https://disfold.com/company/x-fab-silicon-foundries-se/",
        "company_name": "X-FAB Silicon Foundries SE",
        "country": "Belgium",
        "employees_number": "4,000",
        "ceo": "Mr. Rudi  De Winter",
        "market_cap": "\u20ac1.15 Billion",
        "id": "",
        "founding_date": "",
        "location_city": "Tessenderlo, Belgium",
        "industry": "",
        "investors": "",
        "founding_year": "",
        "stock": "",
        "revenue": "",
        "sector": "",
        "absolute_growth_rate_pct": "",
        "compound_annual_growth_rate_cagr_pct": "",
        "address": "",
        "telephone": "",
        "facebook": "",
        "twitter": "",
        "instagram": "",
        "pinterest": "",
        "sales": "",
        "assets": "",
        "area_served": "",
        "price": "",
        "income": "",
        "wikipedia": "",
        "hhid": "",
        "sic_code": "",
        "type": ""
    },
    {
        "website": "https://disfold.com/company/x-legend-entertainment-co-ltd/",
        "company_name": "X-Legend Entertainment Co. Ltd",
        "country": "Taiwan",
        "employees_number": "Not found",
        "ceo": "Not found",
        "market_cap": "TW$4.96 Billion",
        "id": "",
        "founding_date": "",
        "location_city": "Taipei, Taiwan",
        "industry": "",
        "investors": "",
        "founding_year": "",
        "stock": "",
        "revenue": "",
        "sector": "",
        "absolute_growth_rate_pct": "",
        "compound_annual_growth_rate_cagr_pct": "",
        "address": "",
        "telephone": "",
        "facebook": "",
        "twitter": "",
        "instagram": "",
        "pinterest": "",
        "sales": "",
        "assets": "",
        "area_served": "",
        "price": "",
        "income": "",
        "wikipedia": "",
        "hhid": "",
        "sic_code": "",
        "type": ""
    },
    {
        "company_name": "X-FAB SILICON FOUNDRIES SE",
        "revenue": "657000000",
        "income": "83000000",
        "market_cap": "1366000000",
        "employees_number": "",
        "ceo": "",
        "country": "Belgium",
        "wikipedia": "",
        "twitter": "",
        "facebook": "",
        "id": "",
        "founding_date": "",
        "location_city": "Belgium",
        "industry": "",
        "investors": "",
        "founding_year": "",
        "stock": "",
        "sector": "",
        "absolute_growth_rate_pct": "",
        "compound_annual_growth_rate_cagr_pct": "",
        "website": "",
        "address": "",
        "telephone": "",
        "instagram": "",
        "pinterest": "",
        "sales": "",
        "assets": "",
        "area_served": "",
        "price": "",
        "hhid": "",
        "sic_code": "",
        "type": ""
    },
    {
        "id": "32",
        "company_name": "X-Team Careers",
        "website": "x-team.com",
        "location_city": "Austin, TX",
        "stock": "201 to 500 employees",
        "industry": "Internet",
        "founding_year": "2004",
        "country": "United States",
        "founding_date": "",
        "investors": "",
        "revenue": "",
        "sector": "",
        "absolute_growth_rate_pct": "",
        "compound_annual_growth_rate_cagr_pct": "",
        "employees_number": "",
        "market_cap": "",
        "ceo": "",
        "address": "",
        "telephone": "",
        "facebook": "",
        "twitter": "",
        "instagram": "",
        "pinterest": "",
        "sales": "",
        "assets": "",
        "area_served": "",
        "price": "",
        "income": "",
        "wikipedia": "",
        "hhid": "",
        "sic_code": "",
        "type": ""
    },
    {
        "company_name": "X-Legend Entertainment",
        "market_cap": "150000000",
        "price": "1",
        "country": "Taiwan",
        "id": "",
        "founding_date": "",
        "location_city": "Taiwan",
        "industry": "",
        "investors": "",
        "founding_year": "",
        "stock": "",
        "revenue": "",
        "sector": "",
        "absolute_growth_rate_pct": "",
        "compound_annual_growth_rate_cagr_pct": "",
        "employees_number": "",
        "website": "",
        "ceo": "",
        "address": "",
        "telephone": "",
        "facebook": "",
        "twitter": "",
        "instagram": "",
        "pinterest": "",
        "sales": "",
        "assets": "",
        "area_served": "",
        "income": "",
        "wikipedia": "",
        "hhid": "",
        "sic_code": "",
        "type": ""
    }
]